{
    "os": "Linux-5.4.0-135-generic-x86_64-with-glibc2.31",
    "python": "3.9.15",
    "heartbeatAt": "2022-12-18T11:07:35.599509",
    "startedAt": "2022-12-18T11:07:34.959077",
    "docker": null,
    "cuda": null,
    "args": [
        "--dataset",
        "cifar100",
        "--epoch",
        "150",
        "--bs",
        "256",
        "--drop_fc",
        "0.0",
        "--head_size1",
        "4096",
        "--head_size2",
        "1000",
        "--wandb",
        "my-experiment",
        "--lr",
        "5e-4"
    ],
    "state": "running",
    "program": "/home/sungwoopark/dl-experiment/main.py",
    "codePath": "main.py",
    "host": "ubuntu",
    "username": "sungwoopark",
    "executable": "/home/sungwoopark/anaconda3/envs/main/bin/python3",
    "cpu_count": 20,
    "cpu_count_logical": 40,
    "cpu_freq": {
        "current": 1983.0567999999998,
        "min": 1000.0,
        "max": 3200.0
    },
    "cpu_freq_per_core": [
        {
            "current": 999.997,
            "min": 1000.0,
            "max": 3200.0
        },
        {
            "current": 1784.916,
            "min": 1000.0,
            "max": 3200.0
        },
        {
            "current": 2726.827,
            "min": 1000.0,
            "max": 3200.0
        },
        {
            "current": 1176.951,
            "min": 1000.0,
            "max": 3200.0
        },
        {
            "current": 999.996,
            "min": 1000.0,
            "max": 3200.0
        },
        {
            "current": 2745.309,
            "min": 1000.0,
            "max": 3200.0
        },
        {
            "current": 2692.243,
            "min": 1000.0,
            "max": 3200.0
        },
        {
            "current": 2899.999,
            "min": 1000.0,
            "max": 3200.0
        },
        {
            "current": 2296.654,
            "min": 1000.0,
            "max": 3200.0
        },
        {
            "current": 2844.451,
            "min": 1000.0,
            "max": 3200.0
        },
        {
            "current": 1967.666,
            "min": 1000.0,
            "max": 3200.0
        },
        {
            "current": 1179.85,
            "min": 1000.0,
            "max": 3200.0
        },
        {
            "current": 1612.935,
            "min": 1000.0,
            "max": 3200.0
        },
        {
            "current": 2267.831,
            "min": 1000.0,
            "max": 3200.0
        },
        {
            "current": 2439.943,
            "min": 1000.0,
            "max": 3200.0
        },
        {
            "current": 2399.999,
            "min": 1000.0,
            "max": 3200.0
        },
        {
            "current": 1976.902,
            "min": 1000.0,
            "max": 3200.0
        },
        {
            "current": 1202.969,
            "min": 1000.0,
            "max": 3200.0
        },
        {
            "current": 1336.396,
            "min": 1000.0,
            "max": 3200.0
        },
        {
            "current": 1869.088,
            "min": 1000.0,
            "max": 3200.0
        },
        {
            "current": 999.999,
            "min": 1000.0,
            "max": 3200.0
        },
        {
            "current": 1782.992,
            "min": 1000.0,
            "max": 3200.0
        },
        {
            "current": 2848.214,
            "min": 1000.0,
            "max": 3200.0
        },
        {
            "current": 1177.67,
            "min": 1000.0,
            "max": 3200.0
        },
        {
            "current": 999.997,
            "min": 1000.0,
            "max": 3200.0
        },
        {
            "current": 2736.984,
            "min": 1000.0,
            "max": 3200.0
        },
        {
            "current": 2728.503,
            "min": 1000.0,
            "max": 3200.0
        },
        {
            "current": 2899.998,
            "min": 1000.0,
            "max": 3200.0
        },
        {
            "current": 2345.019,
            "min": 1000.0,
            "max": 3200.0
        },
        {
            "current": 2899.625,
            "min": 1000.0,
            "max": 3200.0
        },
        {
            "current": 2226.031,
            "min": 1000.0,
            "max": 3200.0
        },
        {
            "current": 1170.699,
            "min": 1000.0,
            "max": 3200.0
        },
        {
            "current": 1655.376,
            "min": 1000.0,
            "max": 3200.0
        },
        {
            "current": 2330.293,
            "min": 1000.0,
            "max": 3200.0
        },
        {
            "current": 2558.661,
            "min": 1000.0,
            "max": 3200.0
        },
        {
            "current": 2399.997,
            "min": 1000.0,
            "max": 3200.0
        },
        {
            "current": 2251.243,
            "min": 1000.0,
            "max": 3200.0
        },
        {
            "current": 1308.957,
            "min": 1000.0,
            "max": 3200.0
        },
        {
            "current": 1318.184,
            "min": 1000.0,
            "max": 3200.0
        },
        {
            "current": 2065.529,
            "min": 1000.0,
            "max": 3200.0
        }
    ],
    "disk": {
        "total": 405.5688018798828,
        "used": 353.57068252563477
    },
    "gpu": "NVIDIA GeForce RTX 3090",
    "gpu_count": 4,
    "gpu_devices": [
        {
            "name": "NVIDIA GeForce RTX 3090",
            "memory_total": 25447170048
        },
        {
            "name": "NVIDIA GeForce RTX 3090",
            "memory_total": 25447170048
        },
        {
            "name": "NVIDIA GeForce RTX 3090",
            "memory_total": 25447170048
        },
        {
            "name": "NVIDIA GeForce RTX 3090",
            "memory_total": 25447170048
        }
    ],
    "memory": {
        "total": 187.58544921875
    }
}
